update_netrc/__init__.py
update_netrc/cli.py
update_netrc-0.2.0.dist-info/LICENSE.txt
update_netrc-0.2.0.dist-info/METADATA
update_netrc-0.2.0.dist-info/WHEEL
update_netrc-0.2.0.dist-info/entry_points.txt
update_netrc-0.2.0.dist-info/top_level.txt
update_netrc-0.2.0.dist-info/RECORD
