Metadata-Version: 2.2
Name: update-netrc
Version: 0.2.0
Summary: A simple command line utility to update netrc credentials
Author-email: Maerteijn <maerteijn@gmail.com>
License: MIT
Project-URL: Repository, https://github.com/maerteijn/update-netrc
Classifier: Development Status :: 3 - Alpha
Classifier: Environment :: Console
Classifier: Intended Audience :: Developers
Classifier: Intended Audience :: System Administrators
Classifier: License :: OSI Approved :: MIT License
Classifier: Programming Language :: Python :: 3.9
Classifier: Programming Language :: Python :: 3.10
Classifier: Programming Language :: Python :: 3.11
Classifier: Programming Language :: Python :: 3.12
Classifier: Programming Language :: Python :: 3.13
Classifier: Topic :: System :: Systems Administration
Requires-Python: >=3.9
License-File: LICENSE.txt
Provides-Extra: dev
Requires-Dist: pip-tools~=7.3; extra == "dev"
Requires-Dist: ruff~=0.9; extra == "dev"
Requires-Dist: pytest~=7.4; extra == "dev"
Requires-Dist: pytest-cov~=4.0; extra == "dev"
Requires-Dist: mypy~=1.5; extra == "dev"
Requires-Dist: twine~=4.0; extra == "dev"
Provides-Extra: dist
Requires-Dist: build~=1.0; extra == "dist"
